README.md
setup.py
pybayesbandit/__init__.py
pybayesbandit.egg-info/PKG-INFO
pybayesbandit.egg-info/SOURCES.txt
pybayesbandit.egg-info/dependency_links.txt
pybayesbandit.egg-info/not-zip-safe
pybayesbandit.egg-info/top_level.txt
pybayesbandit/bandits/__init__.py
pybayesbandit/bandits/bernoulli.py
pybayesbandit/games/__init__.py
pybayesbandit/games/simpleregret.py
pybayesbandit/games/totalregret.py
pybayesbandit/learners/__init__.py
pybayesbandit/learners/lookahead.py
pybayesbandit/learners/random.py
pybayesbandit/learners/rollout.py
pybayesbandit/learners/thompson.py
pybayesbandit/learners/ucb.py
pybayesbandit/learners/uct.py
pybayesbandit/learners/vi.py
pybayesbandit/mdp/__init__.py
pybayesbandit/mdp/beta_bernoulli.py
pybayesbandit/search/__init__.py
pybayesbandit/search/aotree.py
pybayesbandit/search/mcts.py
scripts/pybayesbandit