Metadata-Version: 1.1
Name: pybayesbandit
Version: 0.0.4
Summary: Bayesian bandits in Python3.
Home-page: https://github.com/thiagopbueno/pybayesbandit
Author: Thiago P. Bueno
Author-email: thiago.pbueno@gmail.com
License: GNU General Public License v3.0
Keywords: rl,bayesian,bandit-learning,belief-planning
Platform: UNKNOWN
Classifier: Development Status :: 3 - Alpha
Classifier: Environment :: Console
Classifier: Intended Audience :: Science/Research
Classifier: License :: OSI Approved :: GNU General Public License v3 (GPLv3)
Classifier: Natural Language :: English
Classifier: Operating System :: OS Independent
Classifier: Programming Language :: Python :: 3
Classifier: Topic :: Scientific/Engineering :: Artificial Intelligence
